flake8_qgis/__init__.py
flake8_qgis/_version.py
flake8_qgis/flake8_qgis.py
flake8_qgis/py.typed
flake8_qgis-1.1.0.dist-info/licenses/LICENSE
flake8_qgis-1.1.0.dist-info/METADATA
flake8_qgis-1.1.0.dist-info/WHEEL
flake8_qgis-1.1.0.dist-info/entry_points.txt
flake8_qgis-1.1.0.dist-info/top_level.txt
flake8_qgis-1.1.0.dist-info/RECORD
