Metadata-Version: 2.4
Name: flake8_qgis
Version: 1.1.0
Summary: Flake8 plugin for QGIS python plugins.
Home-page: https://github.com/GispoCoding/flake8-qgis
Author: Joona Laine
Author-email: info@gispo.fi
Maintainer: Joona Laine
Maintainer-email: info@gispo.fi
License: MIT license
Keywords: flake8,qgis,QGIS,PyQGIS
Classifier: Development Status :: 1 - Planning
Classifier: Intended Audience :: Developers
Classifier: Natural Language :: English
Classifier: Operating System :: OS Independent
Classifier: Programming Language :: Python :: 3
Classifier: Programming Language :: Python :: 3 :: Only
Classifier: Programming Language :: Python :: 3.9
Classifier: Programming Language :: Python :: 3.10
Classifier: Programming Language :: Python :: 3.11
Classifier: Programming Language :: Python :: 3.12
Classifier: Programming Language :: Python :: 3.13
Classifier: Topic :: Software Development
Classifier: Framework :: Flake8
Requires-Python: >=3.9
License-File: LICENSE
Requires-Dist: flake8>=7.2
Dynamic: license-file
